<?xml version="1.0" encoding="UTF-8" standalone="no"?><Gesture Date="Saturday, April 15, 2023" Milliseconds="2519" Name="triangle08" NumPts="236" Time="9:52:46 PM">
  <Point T="1681609963527" X="182.0" Y="63.0"/>
  <Point T="1681609963527" X="173.0" Y="72.0"/>
  <Point T="1681609963531" X="170.0" Y="75.0"/>
  <Point T="1681609963541" X="168.0" Y="79.0"/>
  <Point T="1681609963549" X="166.0" Y="84.0"/>
  <Point T="1681609963558" X="163.0" Y="87.0"/>
  <Point T="1681609963564" X="161.0" Y="90.0"/>
  <Point T="1681609963574" X="157.0" Y="95.0"/>
  <Point T="1681609963582" X="155.0" Y="98.0"/>
  <Point T="1681609963591" X="152.0" Y="101.0"/>
  <Point T="1681609963599" X="150.0" Y="104.0"/>
  <Point T="1681609963607" X="148.0" Y="106.0"/>
  <Point T="1681609963615" X="146.0" Y="109.0"/>
  <Point T="1681609963625" X="144.0" Y="111.0"/>
  <Point T="1681609963632" X="143.0" Y="113.0"/>
  <Point T="1681609963641" X="142.0" Y="116.0"/>
  <Point T="1681609963649" X="140.0" Y="118.0"/>
  <Point T="1681609963657" X="138.0" Y="120.0"/>
  <Point T="1681609963665" X="136.0" Y="122.0"/>
  <Point T="1681609963675" X="134.0" Y="125.0"/>
  <Point T="1681609963683" X="132.0" Y="127.0"/>
  <Point T="1681609963691" X="131.0" Y="130.0"/>
  <Point T="1681609963699" X="129.0" Y="132.0"/>
  <Point T="1681609963708" X="127.0" Y="134.0"/>
  <Point T="1681609963716" X="125.0" Y="137.0"/>
  <Point T="1681609963724" X="123.0" Y="141.0"/>
  <Point T="1681609963733" X="121.0" Y="145.0"/>
  <Point T="1681609963742" X="119.0" Y="148.0"/>
  <Point T="1681609963750" X="117.0" Y="152.0"/>
  <Point T="1681609963758" X="114.0" Y="155.0"/>
  <Point T="1681609963765" X="112.0" Y="158.0"/>
  <Point T="1681609963776" X="109.0" Y="162.0"/>
  <Point T="1681609963783" X="107.0" Y="165.0"/>
  <Point T="1681609963792" X="105.0" Y="169.0"/>
  <Point T="1681609963799" X="103.0" Y="172.0"/>
  <Point T="1681609963809" X="101.0" Y="175.0"/>
  <Point T="1681609963816" X="99.0" Y="178.0"/>
  <Point T="1681609963824" X="97.0" Y="181.0"/>
  <Point T="1681609963832" X="95.0" Y="184.0"/>
  <Point T="1681609963844" X="92.0" Y="187.0"/>
  <Point T="1681609963849" X="90.0" Y="190.0"/>
  <Point T="1681609963859" X="88.0" Y="193.0"/>
  <Point T="1681609963865" X="87.0" Y="195.0"/>
  <Point T="1681609963876" X="85.0" Y="197.0"/>
  <Point T="1681609963884" X="83.0" Y="199.0"/>
  <Point T="1681609963893" X="82.0" Y="201.0"/>
  <Point T="1681609963904" X="80.0" Y="203.0"/>
  <Point T="1681609963908" X="79.0" Y="204.0"/>
  <Point T="1681609963917" X="78.0" Y="206.0"/>
  <Point T="1681609963925" X="77.0" Y="207.0"/>
  <Point T="1681609963936" X="76.0" Y="209.0"/>
  <Point T="1681609963941" X="75.0" Y="210.0"/>
  <Point T="1681609963953" X="74.0" Y="211.0"/>
  <Point T="1681609963957" X="73.0" Y="212.0"/>
  <Point T="1681609963969" X="73.0" Y="213.0"/>
  <Point T="1681609963974" X="73.0" Y="214.0"/>
  <Point T="1681609963982" X="72.0" Y="215.0"/>
  <Point T="1681609963989" X="72.0" Y="215.0"/>
  <Point T="1681609963997" X="71.0" Y="216.0"/>
  <Point T="1681609964008" X="71.0" Y="216.0"/>
  <Point T="1681609964191" X="71.0" Y="217.0"/>
  <Point T="1681609964202" X="71.0" Y="217.0"/>
  <Point T="1681609964215" X="72.0" Y="217.0"/>
  <Point T="1681609964234" X="72.0" Y="218.0"/>
  <Point T="1681609964243" X="73.0" Y="218.0"/>
  <Point T="1681609964252" X="73.0" Y="218.0"/>
  <Point T="1681609964263" X="73.0" Y="218.0"/>
  <Point T="1681609964267" X="74.0" Y="218.0"/>
  <Point T="1681609964275" X="74.0" Y="219.0"/>
  <Point T="1681609964286" X="75.0" Y="219.0"/>
  <Point T="1681609964294" X="76.0" Y="220.0"/>
  <Point T="1681609964301" X="77.0" Y="220.0"/>
  <Point T="1681609964312" X="78.0" Y="220.0"/>
  <Point T="1681609964318" X="78.0" Y="221.0"/>
  <Point T="1681609964326" X="80.0" Y="221.0"/>
  <Point T="1681609964334" X="82.0" Y="222.0"/>
  <Point T="1681609964345" X="83.0" Y="222.0"/>
  <Point T="1681609964354" X="85.0" Y="223.0"/>
  <Point T="1681609964359" X="87.0" Y="223.0"/>
  <Point T="1681609964369" X="89.0" Y="223.0"/>
  <Point T="1681609964376" X="92.0" Y="224.0"/>
  <Point T="1681609964379" X="94.0" Y="224.0"/>
  <Point T="1681609964379" X="97.0" Y="225.0"/>
  <Point T="1681609964397" X="101.0" Y="225.0"/>
  <Point T="1681609964397" X="104.0" Y="226.0"/>
  <Point T="1681609964412" X="107.0" Y="226.0"/>
  <Point T="1681609964427" X="109.0" Y="226.0"/>
  <Point T="1681609964428" X="112.0" Y="227.0"/>
  <Point T="1681609964443" X="114.0" Y="227.0"/>
  <Point T="1681609964443" X="116.0" Y="227.0"/>
  <Point T="1681609964460" X="119.0" Y="227.0"/>
  <Point T="1681609964467" X="122.0" Y="227.0"/>
  <Point T="1681609964476" X="126.0" Y="228.0"/>
  <Point T="1681609964476" X="129.0" Y="228.0"/>
  <Point T="1681609964494" X="132.0" Y="228.0"/>
  <Point T="1681609964494" X="134.0" Y="228.0"/>
  <Point T="1681609964507" X="137.0" Y="228.0"/>
  <Point T="1681609964507" X="139.0" Y="228.0"/>
  <Point T="1681609964523" X="142.0" Y="228.0"/>
  <Point T="1681609964523" X="145.0" Y="229.0"/>
  <Point T="1681609964538" X="148.0" Y="229.0"/>
  <Point T="1681609964538" X="151.0" Y="229.0"/>
  <Point T="1681609964555" X="154.0" Y="229.0"/>
  <Point T="1681609964555" X="157.0" Y="229.0"/>
  <Point T="1681609964572" X="159.0" Y="229.0"/>
  <Point T="1681609964572" X="162.0" Y="229.0"/>
  <Point T="1681609964588" X="167.0" Y="229.0"/>
  <Point T="1681609964588" X="170.0" Y="229.0"/>
  <Point T="1681609964603" X="173.0" Y="229.0"/>
  <Point T="1681609964603" X="177.0" Y="228.0"/>
  <Point T="1681609964619" X="180.0" Y="228.0"/>
  <Point T="1681609964634" X="184.0" Y="228.0"/>
  <Point T="1681609964635" X="189.0" Y="228.0"/>
  <Point T="1681609964635" X="193.0" Y="228.0"/>
  <Point T="1681609964651" X="197.0" Y="227.0"/>
  <Point T="1681609964668" X="201.0" Y="227.0"/>
  <Point T="1681609964668" X="206.0" Y="226.0"/>
  <Point T="1681609964683" X="211.0" Y="226.0"/>
  <Point T="1681609964683" X="215.0" Y="225.0"/>
  <Point T="1681609964698" X="219.0" Y="225.0"/>
  <Point T="1681609964698" X="223.0" Y="224.0"/>
  <Point T="1681609964714" X="228.0" Y="223.0"/>
  <Point T="1681609964714" X="232.0" Y="223.0"/>
  <Point T="1681609964730" X="237.0" Y="222.0"/>
  <Point T="1681609964730" X="241.0" Y="221.0"/>
  <Point T="1681609964745" X="245.0" Y="221.0"/>
  <Point T="1681609964745" X="249.0" Y="220.0"/>
  <Point T="1681609964761" X="253.0" Y="220.0"/>
  <Point T="1681609964767" X="257.0" Y="219.0"/>
  <Point T="1681609964777" X="260.0" Y="219.0"/>
  <Point T="1681609964793" X="262.0" Y="219.0"/>
  <Point T="1681609964793" X="264.0" Y="219.0"/>
  <Point T="1681609964808" X="267.0" Y="219.0"/>
  <Point T="1681609964808" X="268.0" Y="219.0"/>
  <Point T="1681609964824" X="270.0" Y="219.0"/>
  <Point T="1681609964824" X="271.0" Y="219.0"/>
  <Point T="1681609964843" X="272.0" Y="219.0"/>
  <Point T="1681609964856" X="273.0" Y="219.0"/>
  <Point T="1681609964867" X="273.0" Y="219.0"/>
  <Point T="1681609964872" X="274.0" Y="219.0"/>
  <Point T="1681609964872" X="274.0" Y="219.0"/>
  <Point T="1681609965204" X="274.0" Y="218.0"/>
  <Point T="1681609965220" X="274.0" Y="217.0"/>
  <Point T="1681609965220" X="274.0" Y="216.0"/>
  <Point T="1681609965235" X="273.0" Y="215.0"/>
  <Point T="1681609965235" X="273.0" Y="213.0"/>
  <Point T="1681609965251" X="272.0" Y="212.0"/>
  <Point T="1681609965251" X="272.0" Y="210.0"/>
  <Point T="1681609965268" X="271.0" Y="208.0"/>
  <Point T="1681609965268" X="270.0" Y="206.0"/>
  <Point T="1681609965283" X="268.0" Y="204.0"/>
  <Point T="1681609965283" X="267.0" Y="201.0"/>
  <Point T="1681609965298" X="266.0" Y="200.0"/>
  <Point T="1681609965305" X="265.0" Y="198.0"/>
  <Point T="1681609965315" X="263.0" Y="196.0"/>
  <Point T="1681609965330" X="262.0" Y="194.0"/>
  <Point T="1681609965330" X="260.0" Y="191.0"/>
  <Point T="1681609965347" X="258.0" Y="189.0"/>
  <Point T="1681609965347" X="257.0" Y="187.0"/>
  <Point T="1681609965347" X="255.0" Y="185.0"/>
  <Point T="1681609965368" X="254.0" Y="183.0"/>
  <Point T="1681609965378" X="252.0" Y="181.0"/>
  <Point T="1681609965378" X="252.0" Y="180.0"/>
  <Point T="1681609965394" X="251.0" Y="178.0"/>
  <Point T="1681609965395" X="250.0" Y="176.0"/>
  <Point T="1681609965410" X="248.0" Y="175.0"/>
  <Point T="1681609965419" X="247.0" Y="173.0"/>
  <Point T="1681609965426" X="246.0" Y="171.0"/>
  <Point T="1681609965435" X="245.0" Y="169.0"/>
  <Point T="1681609965444" X="243.0" Y="167.0"/>
  <Point T="1681609965452" X="242.0" Y="165.0"/>
  <Point T="1681609965457" X="241.0" Y="163.0"/>
  <Point T="1681609965457" X="239.0" Y="161.0"/>
  <Point T="1681609965474" X="238.0" Y="159.0"/>
  <Point T="1681609965474" X="237.0" Y="157.0"/>
  <Point T="1681609965490" X="235.0" Y="154.0"/>
  <Point T="1681609965490" X="233.0" Y="151.0"/>
  <Point T="1681609965505" X="232.0" Y="148.0"/>
  <Point T="1681609965505" X="231.0" Y="146.0"/>
  <Point T="1681609965522" X="230.0" Y="143.0"/>
  <Point T="1681609965522" X="229.0" Y="141.0"/>
  <Point T="1681609965538" X="228.0" Y="139.0"/>
  <Point T="1681609965544" X="227.0" Y="136.0"/>
  <Point T="1681609965554" X="225.0" Y="134.0"/>
  <Point T="1681609965570" X="224.0" Y="132.0"/>
  <Point T="1681609965570" X="222.0" Y="129.0"/>
  <Point T="1681609965586" X="221.0" Y="127.0"/>
  <Point T="1681609965586" X="220.0" Y="125.0"/>
  <Point T="1681609965601" X="218.0" Y="122.0"/>
  <Point T="1681609965601" X="217.0" Y="121.0"/>
  <Point T="1681609965617" X="216.0" Y="119.0"/>
  <Point T="1681609965617" X="215.0" Y="118.0"/>
  <Point T="1681609965634" X="214.0" Y="116.0"/>
  <Point T="1681609965634" X="213.0" Y="115.0"/>
  <Point T="1681609965649" X="212.0" Y="114.0"/>
  <Point T="1681609965649" X="212.0" Y="112.0"/>
  <Point T="1681609965669" X="211.0" Y="111.0"/>
  <Point T="1681609965669" X="210.0" Y="110.0"/>
  <Point T="1681609965682" X="209.0" Y="108.0"/>
  <Point T="1681609965682" X="208.0" Y="106.0"/>
  <Point T="1681609965697" X="207.0" Y="104.0"/>
  <Point T="1681609965697" X="206.0" Y="103.0"/>
  <Point T="1681609965713" X="206.0" Y="101.0"/>
  <Point T="1681609965728" X="205.0" Y="100.0"/>
  <Point T="1681609965728" X="204.0" Y="99.0"/>
  <Point T="1681609965744" X="203.0" Y="97.0"/>
  <Point T="1681609965760" X="202.0" Y="96.0"/>
  <Point T="1681609965760" X="202.0" Y="95.0"/>
  <Point T="1681609965769" X="201.0" Y="93.0"/>
  <Point T="1681609965777" X="200.0" Y="92.0"/>
  <Point T="1681609965777" X="200.0" Y="91.0"/>
  <Point T="1681609965791" X="199.0" Y="90.0"/>
  <Point T="1681609965808" X="198.0" Y="89.0"/>
  <Point T="1681609965808" X="197.0" Y="88.0"/>
  <Point T="1681609965824" X="197.0" Y="87.0"/>
  <Point T="1681609965824" X="197.0" Y="86.0"/>
  <Point T="1681609965840" X="196.0" Y="85.0"/>
  <Point T="1681609965840" X="196.0" Y="84.0"/>
  <Point T="1681609965855" X="195.0" Y="83.0"/>
  <Point T="1681609965855" X="195.0" Y="82.0"/>
  <Point T="1681609965873" X="194.0" Y="82.0"/>
  <Point T="1681609965873" X="194.0" Y="81.0"/>
  <Point T="1681609965888" X="194.0" Y="81.0"/>
  <Point T="1681609965888" X="194.0" Y="80.0"/>
  <Point T="1681609965903" X="193.0" Y="79.0"/>
  <Point T="1681609965919" X="193.0" Y="79.0"/>
  <Point T="1681609965919" X="193.0" Y="78.0"/>
  <Point T="1681609965935" X="193.0" Y="77.0"/>
  <Point T="1681609965935" X="193.0" Y="77.0"/>
  <Point T="1681609965950" X="193.0" Y="76.0"/>
  <Point T="1681609965950" X="192.0" Y="76.0"/>
  <Point T="1681609965969" X="192.0" Y="75.0"/>
  <Point T="1681609965969" X="192.0" Y="75.0"/>
  <Point T="1681609965983" X="192.0" Y="74.0"/>
  <Point T="1681609965983" X="192.0" Y="74.0"/>
  <Point T="1681609966046" X="193.0" Y="74.0"/>
</Gesture>