<?xml version="1.0" encoding="UTF-8" standalone="no"?><Gesture Date="Friday, April 14, 2023" Milliseconds="1316" Name="zigzag01" NumPts="233" Time="10:13:59 PM">
  <Point T="1681524837717" X="64.0" Y="306.0"/>
  <Point T="1681524837718" X="63.0" Y="306.0"/>
  <Point T="1681524837870" X="63.0" Y="305.0"/>
  <Point T="1681524837871" X="64.0" Y="304.0"/>
  <Point T="1681524837875" X="64.0" Y="302.0"/>
  <Point T="1681524837883" X="66.0" Y="300.0"/>
  <Point T="1681524837888" X="68.0" Y="296.0"/>
  <Point T="1681524837892" X="69.0" Y="294.0"/>
  <Point T="1681524837896" X="70.0" Y="292.0"/>
  <Point T="1681524837900" X="70.0" Y="291.0"/>
  <Point T="1681524837904" X="72.0" Y="288.0"/>
  <Point T="1681524837908" X="74.0" Y="285.0"/>
  <Point T="1681524837912" X="75.0" Y="282.0"/>
  <Point T="1681524837916" X="77.0" Y="278.0"/>
  <Point T="1681524837920" X="79.0" Y="275.0"/>
  <Point T="1681524837924" X="80.0" Y="273.0"/>
  <Point T="1681524837928" X="81.0" Y="270.0"/>
  <Point T="1681524837933" X="83.0" Y="268.0"/>
  <Point T="1681524837938" X="83.0" Y="266.0"/>
  <Point T="1681524837941" X="83.0" Y="266.0"/>
  <Point T="1681524837945" X="84.0" Y="264.0"/>
  <Point T="1681524837949" X="85.0" Y="262.0"/>
  <Point T="1681524837955" X="86.0" Y="260.0"/>
  <Point T="1681524837963" X="87.0" Y="258.0"/>
  <Point T="1681524837967" X="88.0" Y="257.0"/>
  <Point T="1681524837971" X="88.0" Y="256.0"/>
  <Point T="1681524837975" X="89.0" Y="255.0"/>
  <Point T="1681524837979" X="89.0" Y="254.0"/>
  <Point T="1681524837983" X="89.0" Y="253.0"/>
  <Point T="1681524837987" X="89.0" Y="252.0"/>
  <Point T="1681524837991" X="90.0" Y="251.0"/>
  <Point T="1681524837995" X="90.0" Y="251.0"/>
  <Point T="1681524837999" X="90.0" Y="251.0"/>
  <Point T="1681524838004" X="90.0" Y="251.0"/>
  <Point T="1681524838008" X="90.0" Y="250.0"/>
  <Point T="1681524838012" X="90.0" Y="250.0"/>
  <Point T="1681524838016" X="90.0" Y="249.0"/>
  <Point T="1681524838020" X="91.0" Y="249.0"/>
  <Point T="1681524838025" X="91.0" Y="249.0"/>
  <Point T="1681524838032" X="91.0" Y="249.0"/>
  <Point T="1681524838041" X="91.0" Y="249.0"/>
  <Point T="1681524838062" X="91.0" Y="249.0"/>
  <Point T="1681524838066" X="91.0" Y="249.0"/>
  <Point T="1681524838070" X="91.0" Y="249.0"/>
  <Point T="1681524838075" X="91.0" Y="249.0"/>
  <Point T="1681524838079" X="91.0" Y="249.0"/>
  <Point T="1681524838083" X="91.0" Y="249.0"/>
  <Point T="1681524838087" X="92.0" Y="250.0"/>
  <Point T="1681524838091" X="92.0" Y="250.0"/>
  <Point T="1681524838095" X="92.0" Y="251.0"/>
  <Point T="1681524838099" X="92.0" Y="251.0"/>
  <Point T="1681524838103" X="92.0" Y="252.0"/>
  <Point T="1681524838108" X="93.0" Y="253.0"/>
  <Point T="1681524838112" X="93.0" Y="254.0"/>
  <Point T="1681524838120" X="94.0" Y="255.0"/>
  <Point T="1681524838124" X="96.0" Y="257.0"/>
  <Point T="1681524838128" X="97.0" Y="258.0"/>
  <Point T="1681524838133" X="98.0" Y="260.0"/>
  <Point T="1681524838137" X="99.0" Y="261.0"/>
  <Point T="1681524838141" X="101.0" Y="263.0"/>
  <Point T="1681524838145" X="102.0" Y="264.0"/>
  <Point T="1681524838149" X="104.0" Y="266.0"/>
  <Point T="1681524838154" X="106.0" Y="268.0"/>
  <Point T="1681524838158" X="108.0" Y="270.0"/>
  <Point T="1681524838162" X="110.0" Y="272.0"/>
  <Point T="1681524838166" X="113.0" Y="274.0"/>
  <Point T="1681524838170" X="116.0" Y="277.0"/>
  <Point T="1681524838174" X="118.0" Y="279.0"/>
  <Point T="1681524838178" X="121.0" Y="281.0"/>
  <Point T="1681524838182" X="123.0" Y="284.0"/>
  <Point T="1681524838187" X="127.0" Y="286.0"/>
  <Point T="1681524838191" X="128.0" Y="287.0"/>
  <Point T="1681524838199" X="130.0" Y="289.0"/>
  <Point T="1681524838203" X="133.0" Y="292.0"/>
  <Point T="1681524838207" X="134.0" Y="293.0"/>
  <Point T="1681524838212" X="135.0" Y="294.0"/>
  <Point T="1681524838217" X="136.0" Y="295.0"/>
  <Point T="1681524838220" X="137.0" Y="296.0"/>
  <Point T="1681524838225" X="138.0" Y="297.0"/>
  <Point T="1681524838228" X="139.0" Y="297.0"/>
  <Point T="1681524838233" X="139.0" Y="298.0"/>
  <Point T="1681524838237" X="140.0" Y="298.0"/>
  <Point T="1681524838241" X="140.0" Y="299.0"/>
  <Point T="1681524838246" X="140.0" Y="299.0"/>
  <Point T="1681524838249" X="141.0" Y="299.0"/>
  <Point T="1681524838255" X="141.0" Y="300.0"/>
  <Point T="1681524838260" X="141.0" Y="300.0"/>
  <Point T="1681524838263" X="141.0" Y="300.0"/>
  <Point T="1681524838267" X="141.0" Y="300.0"/>
  <Point T="1681524838271" X="141.0" Y="300.0"/>
  <Point T="1681524838279" X="142.0" Y="300.0"/>
  <Point T="1681524838283" X="142.0" Y="300.0"/>
  <Point T="1681524838288" X="142.0" Y="300.0"/>
  <Point T="1681524838299" X="142.0" Y="300.0"/>
  <Point T="1681524838303" X="142.0" Y="300.0"/>
  <Point T="1681524838308" X="142.0" Y="299.0"/>
  <Point T="1681524838312" X="142.0" Y="299.0"/>
  <Point T="1681524838316" X="142.0" Y="298.0"/>
  <Point T="1681524838320" X="143.0" Y="297.0"/>
  <Point T="1681524838325" X="143.0" Y="296.0"/>
  <Point T="1681524838329" X="143.0" Y="294.0"/>
  <Point T="1681524838334" X="144.0" Y="292.0"/>
  <Point T="1681524838338" X="144.0" Y="290.0"/>
  <Point T="1681524838342" X="145.0" Y="288.0"/>
  <Point T="1681524838346" X="146.0" Y="285.0"/>
  <Point T="1681524838350" X="147.0" Y="283.0"/>
  <Point T="1681524838361" X="148.0" Y="280.0"/>
  <Point T="1681524838363" X="150.0" Y="276.0"/>
  <Point T="1681524838366" X="151.0" Y="274.0"/>
  <Point T="1681524838371" X="152.0" Y="273.0"/>
  <Point T="1681524838375" X="153.0" Y="271.0"/>
  <Point T="1681524838379" X="154.0" Y="270.0"/>
  <Point T="1681524838383" X="155.0" Y="268.0"/>
  <Point T="1681524838388" X="156.0" Y="266.0"/>
  <Point T="1681524838392" X="156.0" Y="264.0"/>
  <Point T="1681524838396" X="157.0" Y="263.0"/>
  <Point T="1681524838400" X="158.0" Y="262.0"/>
  <Point T="1681524838403" X="159.0" Y="261.0"/>
  <Point T="1681524838408" X="160.0" Y="260.0"/>
  <Point T="1681524838412" X="160.0" Y="259.0"/>
  <Point T="1681524838416" X="161.0" Y="258.0"/>
  <Point T="1681524838420" X="161.0" Y="258.0"/>
  <Point T="1681524838425" X="161.0" Y="257.0"/>
  <Point T="1681524838428" X="161.0" Y="257.0"/>
  <Point T="1681524838438" X="162.0" Y="257.0"/>
  <Point T="1681524838442" X="162.0" Y="256.0"/>
  <Point T="1681524838445" X="162.0" Y="256.0"/>
  <Point T="1681524838450" X="163.0" Y="256.0"/>
  <Point T="1681524838454" X="163.0" Y="256.0"/>
  <Point T="1681524838458" X="163.0" Y="256.0"/>
  <Point T="1681524838462" X="163.0" Y="255.0"/>
  <Point T="1681524838467" X="163.0" Y="255.0"/>
  <Point T="1681524838471" X="163.0" Y="255.0"/>
  <Point T="1681524838475" X="163.0" Y="255.0"/>
  <Point T="1681524838479" X="163.0" Y="255.0"/>
  <Point T="1681524838538" X="163.0" Y="255.0"/>
  <Point T="1681524838543" X="163.0" Y="255.0"/>
  <Point T="1681524838546" X="163.0" Y="255.0"/>
  <Point T="1681524838552" X="163.0" Y="255.0"/>
  <Point T="1681524838555" X="163.0" Y="256.0"/>
  <Point T="1681524838560" X="163.0" Y="256.0"/>
  <Point T="1681524838563" X="164.0" Y="257.0"/>
  <Point T="1681524838567" X="164.0" Y="257.0"/>
  <Point T="1681524838571" X="164.0" Y="258.0"/>
  <Point T="1681524838577" X="164.0" Y="258.0"/>
  <Point T="1681524838579" X="164.0" Y="259.0"/>
  <Point T="1681524838583" X="164.0" Y="259.0"/>
  <Point T="1681524838587" X="164.0" Y="260.0"/>
  <Point T="1681524838595" X="165.0" Y="261.0"/>
  <Point T="1681524838599" X="165.0" Y="263.0"/>
  <Point T="1681524838603" X="166.0" Y="264.0"/>
  <Point T="1681524838608" X="167.0" Y="265.0"/>
  <Point T="1681524838612" X="168.0" Y="266.0"/>
  <Point T="1681524838616" X="170.0" Y="268.0"/>
  <Point T="1681524838620" X="171.0" Y="269.0"/>
  <Point T="1681524838624" X="172.0" Y="271.0"/>
  <Point T="1681524838628" X="174.0" Y="272.0"/>
  <Point T="1681524838633" X="176.0" Y="274.0"/>
  <Point T="1681524838637" X="178.0" Y="276.0"/>
  <Point T="1681524838641" X="180.0" Y="279.0"/>
  <Point T="1681524838645" X="182.0" Y="281.0"/>
  <Point T="1681524838650" X="185.0" Y="284.0"/>
  <Point T="1681524838654" X="187.0" Y="286.0"/>
  <Point T="1681524838658" X="189.0" Y="288.0"/>
  <Point T="1681524838662" X="193.0" Y="291.0"/>
  <Point T="1681524838666" X="195.0" Y="293.0"/>
  <Point T="1681524838674" X="197.0" Y="295.0"/>
  <Point T="1681524838678" X="198.0" Y="297.0"/>
  <Point T="1681524838682" X="200.0" Y="299.0"/>
  <Point T="1681524838687" X="202.0" Y="300.0"/>
  <Point T="1681524838691" X="203.0" Y="302.0"/>
  <Point T="1681524838695" X="204.0" Y="303.0"/>
  <Point T="1681524838699" X="205.0" Y="304.0"/>
  <Point T="1681524838703" X="206.0" Y="305.0"/>
  <Point T="1681524838708" X="207.0" Y="306.0"/>
  <Point T="1681524838712" X="208.0" Y="306.0"/>
  <Point T="1681524838716" X="209.0" Y="307.0"/>
  <Point T="1681524838720" X="209.0" Y="307.0"/>
  <Point T="1681524838724" X="210.0" Y="308.0"/>
  <Point T="1681524838728" X="210.0" Y="308.0"/>
  <Point T="1681524838733" X="210.0" Y="308.0"/>
  <Point T="1681524838737" X="211.0" Y="308.0"/>
  <Point T="1681524838741" X="211.0" Y="308.0"/>
  <Point T="1681524838745" X="211.0" Y="308.0"/>
  <Point T="1681524838753" X="212.0" Y="308.0"/>
  <Point T="1681524838758" X="212.0" Y="308.0"/>
  <Point T="1681524838762" X="212.0" Y="308.0"/>
  <Point T="1681524838766" X="212.0" Y="308.0"/>
  <Point T="1681524838770" X="212.0" Y="308.0"/>
  <Point T="1681524838775" X="212.0" Y="308.0"/>
  <Point T="1681524838781" X="213.0" Y="308.0"/>
  <Point T="1681524838783" X="213.0" Y="308.0"/>
  <Point T="1681524838787" X="213.0" Y="307.0"/>
  <Point T="1681524838791" X="214.0" Y="305.0"/>
  <Point T="1681524838795" X="214.0" Y="303.0"/>
  <Point T="1681524838799" X="215.0" Y="302.0"/>
  <Point T="1681524838803" X="216.0" Y="301.0"/>
  <Point T="1681524838808" X="217.0" Y="299.0"/>
  <Point T="1681524838812" X="218.0" Y="297.0"/>
  <Point T="1681524838816" X="219.0" Y="294.0"/>
  <Point T="1681524838820" X="222.0" Y="289.0"/>
  <Point T="1681524838824" X="223.0" Y="286.0"/>
  <Point T="1681524838832" X="226.0" Y="282.0"/>
  <Point T="1681524838837" X="229.0" Y="277.0"/>
  <Point T="1681524838841" X="231.0" Y="274.0"/>
  <Point T="1681524838845" X="232.0" Y="271.0"/>
  <Point T="1681524838849" X="234.0" Y="268.0"/>
  <Point T="1681524838853" X="235.0" Y="266.0"/>
  <Point T="1681524838857" X="236.0" Y="265.0"/>
  <Point T="1681524838862" X="238.0" Y="261.0"/>
  <Point T="1681524838867" X="240.0" Y="257.0"/>
  <Point T="1681524838871" X="241.0" Y="255.0"/>
  <Point T="1681524838875" X="242.0" Y="254.0"/>
  <Point T="1681524838879" X="243.0" Y="252.0"/>
  <Point T="1681524838884" X="244.0" Y="250.0"/>
  <Point T="1681524838888" X="245.0" Y="248.0"/>
  <Point T="1681524838891" X="246.0" Y="247.0"/>
  <Point T="1681524838895" X="247.0" Y="246.0"/>
  <Point T="1681524838899" X="247.0" Y="244.0"/>
  <Point T="1681524838903" X="248.0" Y="243.0"/>
  <Point T="1681524838912" X="248.0" Y="242.0"/>
  <Point T="1681524838916" X="249.0" Y="242.0"/>
  <Point T="1681524838920" X="249.0" Y="241.0"/>
  <Point T="1681524838924" X="249.0" Y="241.0"/>
  <Point T="1681524838928" X="249.0" Y="241.0"/>
  <Point T="1681524838933" X="249.0" Y="240.0"/>
  <Point T="1681524838937" X="250.0" Y="240.0"/>
  <Point T="1681524838941" X="250.0" Y="240.0"/>
  <Point T="1681524838945" X="250.0" Y="240.0"/>
  <Point T="1681524838949" X="250.0" Y="240.0"/>
  <Point T="1681524838954" X="250.0" Y="240.0"/>
  <Point T="1681524839030" X="250.0" Y="240.0"/>
  <Point T="1681524839033" X="250.0" Y="240.0"/>
</Gesture>