<?xml version="1.0" encoding="UTF-8" standalone="no"?><Gesture Date="Friday, April 14, 2023" Milliseconds="980" Name="right_sq_bracket01" NumPts="103" Time="9:46:01 PM">
  <Point T="1681523160348" X="161.0" Y="116.0"/>
  <Point T="1681523160348" X="177.0" Y="115.0"/>
  <Point T="1681523160358" X="182.0" Y="115.0"/>
  <Point T="1681523160365" X="188.0" Y="115.0"/>
  <Point T="1681523160375" X="193.0" Y="115.0"/>
  <Point T="1681523160381" X="199.0" Y="115.0"/>
  <Point T="1681523160390" X="206.0" Y="115.0"/>
  <Point T="1681523160398" X="212.0" Y="115.0"/>
  <Point T="1681523160412" X="218.0" Y="115.0"/>
  <Point T="1681523160415" X="224.0" Y="115.0"/>
  <Point T="1681523160427" X="229.0" Y="115.0"/>
  <Point T="1681523160431" X="233.0" Y="115.0"/>
  <Point T="1681523160439" X="237.0" Y="115.0"/>
  <Point T="1681523160448" X="240.0" Y="116.0"/>
  <Point T="1681523160458" X="244.0" Y="116.0"/>
  <Point T="1681523160464" X="246.0" Y="116.0"/>
  <Point T="1681523160472" X="248.0" Y="116.0"/>
  <Point T="1681523160488" X="249.0" Y="116.0"/>
  <Point T="1681523160496" X="250.0" Y="116.0"/>
  <Point T="1681523160503" X="251.0" Y="116.0"/>
  <Point T="1681523160512" X="252.0" Y="116.0"/>
  <Point T="1681523160521" X="252.0" Y="116.0"/>
  <Point T="1681523160528" X="253.0" Y="116.0"/>
  <Point T="1681523160533" X="253.0" Y="116.0"/>
  <Point T="1681523160635" X="253.0" Y="117.0"/>
  <Point T="1681523160643" X="253.0" Y="117.0"/>
  <Point T="1681523160651" X="253.0" Y="119.0"/>
  <Point T="1681523160660" X="253.0" Y="121.0"/>
  <Point T="1681523160667" X="253.0" Y="123.0"/>
  <Point T="1681523160676" X="253.0" Y="126.0"/>
  <Point T="1681523160684" X="253.0" Y="129.0"/>
  <Point T="1681523160692" X="254.0" Y="132.0"/>
  <Point T="1681523160700" X="254.0" Y="137.0"/>
  <Point T="1681523160712" X="254.0" Y="142.0"/>
  <Point T="1681523160716" X="255.0" Y="146.0"/>
  <Point T="1681523160724" X="255.0" Y="151.0"/>
  <Point T="1681523160732" X="256.0" Y="156.0"/>
  <Point T="1681523160741" X="256.0" Y="161.0"/>
  <Point T="1681523160748" X="257.0" Y="167.0"/>
  <Point T="1681523160758" X="257.0" Y="173.0"/>
  <Point T="1681523160765" X="257.0" Y="179.0"/>
  <Point T="1681523160773" X="257.0" Y="185.0"/>
  <Point T="1681523160781" X="257.0" Y="190.0"/>
  <Point T="1681523160797" X="258.0" Y="196.0"/>
  <Point T="1681523160797" X="258.0" Y="202.0"/>
  <Point T="1681523160813" X="258.0" Y="208.0"/>
  <Point T="1681523160821" X="259.0" Y="213.0"/>
  <Point T="1681523160829" X="259.0" Y="218.0"/>
  <Point T="1681523160837" X="259.0" Y="223.0"/>
  <Point T="1681523160846" X="259.0" Y="228.0"/>
  <Point T="1681523160855" X="259.0" Y="232.0"/>
  <Point T="1681523160862" X="259.0" Y="235.0"/>
  <Point T="1681523160871" X="259.0" Y="239.0"/>
  <Point T="1681523160878" X="259.0" Y="242.0"/>
  <Point T="1681523160888" X="259.0" Y="244.0"/>
  <Point T="1681523160895" X="259.0" Y="247.0"/>
  <Point T="1681523160903" X="259.0" Y="248.0"/>
  <Point T="1681523160913" X="258.0" Y="250.0"/>
  <Point T="1681523160921" X="258.0" Y="251.0"/>
  <Point T="1681523160927" X="258.0" Y="252.0"/>
  <Point T="1681523160937" X="258.0" Y="253.0"/>
  <Point T="1681523160944" X="258.0" Y="254.0"/>
  <Point T="1681523160961" X="258.0" Y="254.0"/>
  <Point T="1681523160970" X="258.0" Y="255.0"/>
  <Point T="1681523160987" X="258.0" Y="255.0"/>
  <Point T="1681523161002" X="258.0" Y="256.0"/>
  <Point T="1681523161029" X="257.0" Y="256.0"/>
  <Point T="1681523161035" X="257.0" Y="256.0"/>
  <Point T="1681523161045" X="256.0" Y="256.0"/>
  <Point T="1681523161052" X="255.0" Y="256.0"/>
  <Point T="1681523161061" X="254.0" Y="256.0"/>
  <Point T="1681523161069" X="253.0" Y="256.0"/>
  <Point T="1681523161077" X="252.0" Y="256.0"/>
  <Point T="1681523161085" X="250.0" Y="256.0"/>
  <Point T="1681523161093" X="249.0" Y="256.0"/>
  <Point T="1681523161102" X="248.0" Y="256.0"/>
  <Point T="1681523161112" X="246.0" Y="256.0"/>
  <Point T="1681523161119" X="244.0" Y="256.0"/>
  <Point T="1681523161128" X="241.0" Y="256.0"/>
  <Point T="1681523161138" X="237.0" Y="255.0"/>
  <Point T="1681523161144" X="233.0" Y="255.0"/>
  <Point T="1681523161153" X="229.0" Y="255.0"/>
  <Point T="1681523161161" X="225.0" Y="255.0"/>
  <Point T="1681523161170" X="220.0" Y="255.0"/>
  <Point T="1681523161178" X="215.0" Y="254.0"/>
  <Point T="1681523161186" X="210.0" Y="254.0"/>
  <Point T="1681523161194" X="206.0" Y="254.0"/>
  <Point T="1681523161203" X="203.0" Y="254.0"/>
  <Point T="1681523161213" X="199.0" Y="254.0"/>
  <Point T="1681523161219" X="196.0" Y="254.0"/>
  <Point T="1681523161228" X="192.0" Y="254.0"/>
  <Point T="1681523161236" X="189.0" Y="254.0"/>
  <Point T="1681523161244" X="188.0" Y="254.0"/>
  <Point T="1681523161253" X="186.0" Y="254.0"/>
  <Point T="1681523161261" X="184.0" Y="254.0"/>
  <Point T="1681523161269" X="183.0" Y="254.0"/>
  <Point T="1681523161278" X="181.0" Y="254.0"/>
  <Point T="1681523161288" X="180.0" Y="254.0"/>
  <Point T="1681523161294" X="179.0" Y="254.0"/>
  <Point T="1681523161303" X="179.0" Y="254.0"/>
  <Point T="1681523161313" X="178.0" Y="254.0"/>
  <Point T="1681523161320" X="178.0" Y="254.0"/>
  <Point T="1681523161328" X="177.0" Y="254.0"/>
</Gesture>